AUTHORS
LICENSE
MANIFEST.in
README.rst
setup.py
pinax/__init__.py
pinax/models/__init__.py
pinax/models/admin.py
pinax/models/managers.py
pinax/models/models.py
pinax/models/query.py
pinax/models/utils.py
pinax/models/tests/__init__.py
pinax/models/tests/models.py
pinax/models/tests/tests.py
pinax/models/tests/urls.py
pinax_models.egg-info/PKG-INFO
pinax_models.egg-info/SOURCES.txt
pinax_models.egg-info/dependency_links.txt
pinax_models.egg-info/not-zip-safe
pinax_models.egg-info/top_level.txt