Metadata-Version: 1.1
Name: pinax-models
Version: 3.0
Summary: Provide Support for Logical Deletes on Models and in the Django Admin
Home-page: http://pinax-models.rtfd.org/
Author: Pinax Developers
Author-email: developers@pinaxproject.com
License: MIT
Platform: UNKNOWN
Classifier: Development Status :: 4 - Beta
Classifier: Environment :: Web Environment
Classifier: Framework :: Django
Classifier: Intended Audience :: Developers
Classifier: License :: OSI Approved :: MIT License
Classifier: Operating System :: OS Independent
Classifier: Programming Language :: Python
Classifier: Programming Language :: Python :: 2
Classifier: Programming Language :: Python :: 3
Classifier: Topic :: Software Development :: Libraries :: Python Modules
